setup.py
src/pytorch_sru.egg-info/PKG-INFO
src/pytorch_sru.egg-info/SOURCES.txt
src/pytorch_sru.egg-info/dependency_links.txt
src/pytorch_sru.egg-info/requires.txt
src/pytorch_sru.egg-info/top_level.txt
src/torchsru/__init__.py
src/torchsru/model.py
src/torchsru/sru.cu