Metadata-Version: 1.1
Name: pytorch-sru
Version: 0.1.3
Summary: Simple Recurrent Unit (SRU) in PyTorch
Home-page: https://github.com/kaniblu/pytorch-sru
Author: Kang Min Yoo
Author-email: k@nib.lu
License: MIT
Keywords: pytorch cuda deep learning
Platform: UNKNOWN
Classifier: Development Status :: 3 - Alpha
Classifier: Intended Audience :: Developers
Classifier: Programming Language :: Python :: 3
